tts_arranger/__init__.py
tts_arranger/tts_abstract_writer.py
tts_arranger/tts_html_converter.py
tts_arranger/tts_processor.py
tts_arranger/tts_simple_writer.py
tts_arranger/tts_writer.py
tts_arranger/data/checkers_default.json
tts_arranger/data/exclude_ids.json
tts_arranger/data/replace.json
tts_arranger/data/replace_de.json
tts_arranger/data/replace_en.json
tts_arranger/examples/tts_project_example.py
tts_arranger/examples/tts_simple_example.py
tts_arranger/items/__init__.py
tts_arranger/items/tts_chapter.py
tts_arranger/items/tts_item.py
tts_arranger/items/tts_project.py
tts_arranger/tts_reader/__init__.py
tts_arranger/tts_reader/checker.py
tts_arranger/tts_reader/tts_abstract_reader.py
tts_arranger/tts_reader/tts_epub_reader.py
tts_arranger/tts_reader/tts_html_based_reader.py
tts_arranger/tts_reader/tts_html_reader.py
tts_arranger/tts_reader/tts_srt_reader.py
tts_arranger/tts_reader/tts_text_reader.py
tts_arranger/utils/__init__.py
tts_arranger/utils/log.py
tts_arranger-0.3.5.1.dist-info/METADATA
tts_arranger-0.3.5.1.dist-info/WHEEL
tts_arranger-0.3.5.1.dist-info/licenses/LICENSE
tts_arranger-0.3.5.1.dist-info/RECORD
