Metadata-Version: 2.1
Name: tts_arranger
Version: 0.3.5.1
Summary: Simplifies arranging text fragments with multiple speakers and processing it with coqui.ai TTS
Project-URL: Bug Tracker, https://github.com/knochenhans/tts_arranger/issues
Project-URL: Homepage, https://github.com/knochenhans/tts_arranger
Author-email: Andre Jonas <nipsky@gmail.com>
License-File: LICENSE
Classifier: License :: OSI Approved :: MIT License
Classifier: Operating System :: OS Independent
Classifier: Programming Language :: Python :: 3
Requires-Python: >=3.7
Requires-Dist: beautifulsoup4>=4.12.2
Requires-Dist: ebooklib>=0.18
Requires-Dist: ffmpeg-python>=0.2.0
Requires-Dist: num2words>=0.5.11
Requires-Dist: pathvalidate>=2.5.2
Requires-Dist: pillow>=9.5.0
Requires-Dist: python-dateutil>=2.8.2
Requires-Dist: requests>=2.28.2
Requires-Dist: scipy>=1.9.0
Requires-Dist: srt>=3.5.2
Requires-Dist: tts>=0.13.3
